<?xml version="1.0" encoding="UTF-8"?>
<vivadoHLSLog:LogRoot xmlns:vivadoHLSLog="www.xilinx.com/vivadoHLSLog">
  <errorLogs>
    <logs>
      <synLog/>
      <simLog/>
      <mgLog/>
      <packageLog/>
      <csimLog/>
    </logs>
  </errorLogs>
  <warningLogs>
    <logs>
      <synLog/>
      <simLog/>
      <mgLog/>
      <packageLog>
        <logs message="WARNING: [IP_Flow 19-4832] The IP name 'cordiccart2pol_ap_fmul_2_max_dsp_32' you have specified is long. The Windows operating system has path length limitations. It is recommended you use shorter names to reduce the likelihood of issues." projectName="cordiccar2pol" solutionName="solution1" date="2020-12-23T21:33:01.868+0800" type="Warning"/>
        <logs message="WARNING: [IP_Flow 19-4832] The IP name 'cordiccart2pol_ap_fdiv_14_no_dsp_32' you have specified is long. The Windows operating system has path length limitations. It is recommended you use shorter names to reduce the likelihood of issues." projectName="cordiccar2pol" solutionName="solution1" date="2020-12-23T21:32:57.078+0800" type="Warning"/>
        <logs message="WARNING: [IP_Flow 19-4832] The IP name 'cordiccart2pol_ap_fcmp_0_no_dsp_32' you have specified is long. The Windows operating system has path length limitations. It is recommended you use shorter names to reduce the likelihood of issues." projectName="cordiccar2pol" solutionName="solution1" date="2020-12-23T21:32:52.851+0800" type="Warning"/>
        <logs message="WARNING: [IP_Flow 19-4832] The IP name 'cordiccart2pol_ap_faddfsub_3_full_dsp_32' you have specified is long. The Windows operating system has path length limitations. It is recommended you use shorter names to reduce the likelihood of issues." projectName="cordiccar2pol" solutionName="solution1" date="2020-12-23T21:32:48.647+0800" type="Warning"/>
        <logs message="WARNING: [IP_Flow 19-4832] The IP name 'cordiccart2pol_ap_fadd_3_full_dsp_32' you have specified is long. The Windows operating system has path length limitations. It is recommended you use shorter names to reduce the likelihood of issues.&#xD;&#xA;create_ip: Time (s): cpu = 00:00:04 ; elapsed = 00:00:08 . Memory (MB): peak = 1033.723 ; gain = 0.000" projectName="cordiccar2pol" solutionName="solution1" date="2020-12-23T21:32:44.122+0800" type="Warning"/>
      </packageLog>
      <csimLog/>
    </logs>
  </warningLogs>
</vivadoHLSLog:LogRoot>
